<window id="502">
	<defaultcontrol always="true">500</defaultcontrol>
	<allowoverlay>yes</allowoverlay>
	<previouswindow>Home</previouswindow>
	<views>50,51,52,63,77,62,67,96,98,64,70,90,91,93</views>
	
	<controls>	
		<control type="group">
			<include>BackgroundDefault</include>
			<include condition="[[!IsEmpty(Skin.String(CustomMusicBGPath)) + [Skin.String(CustomMusicBGType,) | Skin.String(CustomMusicBGType,2) | Skin.String(CustomMusicBGType,3)]] 
			| Skin.String(CustomMusicBGType,4)] + Skin.HasSetting(ApplyAllMusicCustomBG)">BackgroundMusic</include>
			<include>BackgroundMusicFanart</include>
			<include condition="!Skin.HasSetting(DisableVideoPlayingBG)">BackgroundVideoPlaying</include>
			<include condition="!Skin.HasSetting(DisableMusicPlayingBG)">BackgroundMusicPlaying</include>
			<include>BackgroundOpenCloseAnim</include>	
		</control>
		
		<control type="group">
			<visible>!Window.IsActive(MusicInformation) + !Window.IsActive(MovieInformation)</visible>
			<include>MediaInfoOpenCloseAnim</include>
			<include file="ViewsCommon.xml">IconView</include> <!-- 50 -->
			<include file="ViewsCommon.xml">BigIconView</include> <!-- 51 -->
			<include file="ViewsCommon.xml">ListView</include> <!-- 52 -->
			<include file="ViewsCommon.xml">AlbumThumbsView</include> <!-- 63 -->
			<include file="ViewsMusic.xml">MusicWideListView</include> <!-- 77 -->
			<include file="ViewsMusic.xml">MusicListInfoView</include> <!-- 62 -->
			<include file="ViewsMusic.xml">MusicListInfoView2</include> <!-- 67 -->
			<include file="ViewsMusic.xml">MusicListInfoView3</include> <!-- 96 -->
			<include file="ViewsMusic.xml">MusicThumbsInfoView</include> <!-- 98 -->
			<include file="ViewsMusic.xml">MusicWrapListInfoView</include> <!-- 64 -->
			<include file="ViewsMusic.xml">MusicWallView</include> <!-- 70 -->
			<include file="ViewsAddons.xml">AddonsWideListView</include> <!-- 90 -->
			<include file="ViewsAddons.xml">AddonsListInfoView</include> <!-- 91 -->
			<include file="ViewsAddons.xml">AddonsWrapListInfoView</include> <!-- 93 -->
		</control>	
		
		<include condition="!Skin.HasSetting(EnableKioskMode)">MediaMenuBar</include>
		
		<control type="group">
			<description>Top Bar Area</description>
			<include>TopBarImage</include>
			<include>TopBarOpenCloseAnim</include>
			<include>BreadCrumbMusicLibrary</include>
			<include>Notifications</include>
		</control>
	</controls>	
</window>
